FIFO/FIFO_Read.v
module FIFO_Read #(
    parameter ADDR_WIDTH = 3
) (
    // Inputs 
    input wire r_clk,                           // Read clock
    input wire r_rst,                           // Asynchronous reset for the read logic
    input wire r_inc,                           // Read increment signal (triggers a read operation)
    input wire [ADDR_WIDTH : 0] gray_wptr,      // Synchronized Gray-code write pointer from the write clock domain

    // Outputs
    output wire [ADDR_WIDTH : 0] gray_rptr,     // Gray-code read pointer, sent to the write domain for synchronization
    output wire [ADDR_WIDTH - 1 : 0] r_addr,    // Binary read address for the FIFO memory
    output wire EMPTY                           // Flag indicating the FIFO is empty
);

// Internal register to hold the binary value of the read pointer
// It has ADDR_WIDTH + 1 bits to detect when the pointer wraps around
reg [ADDR_WIDTH : 0] bin_rptr;

// Binary to Gray conversion
assign gray_rptr = bin_rptr ^ (bin_rptr >> 1);

// The actual read address is the lower bits of the binary pointer
assign r_addr = bin_rptr [ADDR_WIDTH-1:0];

// Empty Flag: FIFO is empty when the read and write pointers are equal.
assign EMPTY = (gray_wptr == gray_rptr);

always @(posedge r_clk or negedge r_rst) 
    begin
        if (!r_rst) 
            begin
                bin_rptr <= 'b0;
            end   
        else if (r_inc && !EMPTY)
            begin
                // Increment the address
                bin_rptr <= bin_rptr + 1;
            end
    end

endmodule

FIFO/FIFO_Write.v
module FIFO_Write #(
    parameter ADDR_WIDTH = 3
) (
    // Inputs
    input wire w_inc,                               // Write increment signal (triggers a write operation)
    input wire w_clk,                               // Write clock
    input wire w_rst,                               // Asynchronous reset for the write logic
    input wire [ADDR_WIDTH : 0] gray_rptr,          // Synchronized Gray-code read pointer from the read clock domain

    // Outputs
    output wire [ADDR_WIDTH : 0] gray_wptr,         // Gray-code write pointer, sent to the read domain for synchronization
    output wire [ADDR_WIDTH - 1 : 0] w_addr,        // Binary write address for the FIFO memory
    output wire FULL                                // Flag indicating the FIFO is full.
);

// Internal register to hold the binary value of the write pointer
// It has ADDR_WIDTH bits to detect when the pointer wraps around
reg [ADDR_WIDTH : 0] bin_wptr;

// Binary to Gray conversion
assign gray_wptr = bin_wptr ^ (bin_wptr >> 1);

// The actual write address is the lower bits of the binary pointer
assign w_addr = bin_wptr [ADDR_WIDTH - 1 : 0];

// Full flag
assign FULL  = ((~(gray_wptr[(ADDR_WIDTH) : (ADDR_WIDTH - 1)]) == gray_rptr[(ADDR_WIDTH) : (ADDR_WIDTH - 1)]) && (gray_wptr[(ADDR_WIDTH - 2) : 0] == gray_rptr[(ADDR_WIDTH - 2) : 0]));
    
always @(posedge w_clk or negedge w_rst) 
    begin
        if(!w_rst)
            begin
                bin_wptr <= 'b0;
            end
        else if (w_inc && !FULL)
            begin
                // Increment the address
                bin_wptr <= bin_wptr + 1;
            end
    end

endmodule

FIFO/df_sync.v
module df_sync #(
    parameter ADDR_WIDTH = 3
) (
    // Inputs 
    input wire clk,                                 // Destination clock
    input wire rst,                                 // Asynchronous active-low reset
    input wire [ADDR_WIDTH : 0] data_in,            // Input data from the source clock domain

    // Outputs 
    output reg [ADDR_WIDTH : 0] data_out       // Synchronized output data
);

reg [ADDR_WIDTH : 0] ff1;

// Two stages Flop sync
always @(posedge clk or negedge rst) 
    begin
        if (!rst)
            begin
                ff1 <= 0;
                data_out <= 0;
            end
        else 
            begin
                ff1 <= data_in;
                // Assign the synchronized output
                data_out <= ff1;
            end
    end

endmodule

FIFO/fifo_mem.v
module fifo_mem #(
    parameter DATA_WIDTH = 8,
    parameter DEPTH = 8,
    parameter ADDR_WIDTH = 3
) (
    // Inputs
    input wire w_clk,                           // Write Clock
    input wire w_rst,                           // Active low asynchronus reset
    input wire FULL,                            // FIFO full flag
    input wire w_inc,                           // write address increment enable
    input wire [ADDR_WIDTH - 1 : 0] w_addr,     // Write address
    input wire [ADDR_WIDTH - 1 : 0] r_addr,     // Read address
    input wire [DATA_WIDTH - 1 : 0] w_data,     // Write data

    // Outputs
    output wire [DATA_WIDTH - 1 : 0] r_data          // Read data
);

reg [DATA_WIDTH - 1 : 0] ram [0 : DEPTH - 1];

wire w_clken;                       // Write enable
assign w_clken = (w_inc & !FULL);

integer i;

// Write operation
always @(posedge w_clk or negedge w_rst) 
    begin
        if (!w_rst)
            begin
            // Reset the memory content to all zeros
            for (i = 0; i < DEPTH; i = i + 1) 
                begin
                    ram[i] <= 0;
                end
            end
        else if (w_clken)           
            begin
                ram[w_addr] <= w_data;
            end
    end
    
// Read Operation
assign r_data = ram[r_addr];

endmodule

FIFO/ASYC_FIFO_Top.v
module ASYC_FIFO_Top #(
    parameter DATA_WIDTH = 8,
    parameter DEPTH = 8,
    parameter ADDR_WIDTH = 3
) (
    // Inputs
    input wire W_CLK,                           // Write Clock
    input wire W_RST,                           // Write Reset
    input wire W_INC,                           // Write Increment
    input wire R_CLK,                           // Read Clock
    input wire R_RST,                           // Read Reset
    input wire R_INC,                           // Read Increment
    input wire [DATA_WIDTH - 1 : 0] WR_DATA,    // Write Data (Input)

    // Outputs
    output wire FULL,                           // Full Flag
    output wire EMPTY,                          // Empty Flag
    output wire [DATA_WIDTH - 1 : 0] RD_DATA    // Read Data (Output)
);
// Internal Wires
wire [ADDR_WIDTH - 1 : 0] W_ADDR, R_ADDR; 
wire [ADDR_WIDTH : 0] rptr_in, wptr_in;
wire [ADDR_WIDTH : 0] rptr_out, wptr_out;


// Instantiating the Design
fifo_mem #(
            .DATA_WIDTH(DATA_WIDTH),
            .DEPTH(DEPTH),
            .ADDR_WIDTH(ADDR_WIDTH)
) mem (
            .w_clk(W_CLK),
            .w_rst(W_RST),
            .FULL(FULL),
            .w_inc(W_INC),
            .w_addr(W_ADDR),
            .r_addr(R_ADDR),
            .w_data(WR_DATA),
            .r_data(RD_DATA)
);

df_sync #(
            .ADDR_WIDTH(ADDR_WIDTH)
) df1_w (
            .clk(W_CLK),
            .rst(W_RST),
            .data_in(rptr_in),
            .data_out(rptr_out)
);

df_sync #(
            .ADDR_WIDTH(ADDR_WIDTH)
) df2_r (
            .clk(R_CLK),
            .rst(R_RST),
            .data_in(wptr_in),
            .data_out(wptr_out)
);

FIFO_Write #(
            .ADDR_WIDTH(ADDR_WIDTH)
) WR (
            .w_inc(W_INC),
            .w_clk(W_CLK),
            .w_rst(W_RST),
            .gray_rptr(rptr_out),
            .gray_wptr(wptr_in),
            .w_addr(W_ADDR),
            .FULL(FULL)
);

FIFO_Read #(
            .ADDR_WIDTH(ADDR_WIDTH)
) RD (
            .r_clk(R_CLK),
            .r_rst(R_RST),
            .r_inc(R_INC),
            .gray_wptr(wptr_out),
            .gray_rptr(rptr_in),
            .r_addr(R_ADDR),
            .EMPTY(EMPTY)
);

endmodule

FIFO/ASYC_FIFO_tb.v
`timescale 1ns/1ps

module ASYC_FIFO_tb ();

// Parameters
parameter DATA_WIDTH_tb = 8;
parameter DEPTH_tb = 8;
parameter ADDR_WIDTH_tb = 3;
parameter W_CLK_PERIOD = 10;
parameter R_CLK_PERIOD = 25.0;

// DUT Inputs
reg W_CLK_tb;
reg W_RST_tb;
reg W_INC_tb;
reg R_CLK_tb;
reg R_RST_tb;
reg R_INC_tb;
reg [DATA_WIDTH_tb - 1 : 0] WR_DATA_tb;

// DUT Outputs
wire FULL_tb;
wire EMPTY_tb;
wire [DATA_WIDTH_tb - 1 : 0] RD_DATA_tb;

// Test variables
reg [DATA_WIDTH_tb-1:0] expected_data [0:DEPTH_tb-1];
integer wr_index;
integer rd_index;

// Instantiating the DUT
ASYC_FIFO_Top #(
                .DATA_WIDTH(DATA_WIDTH_tb),
                .DEPTH(DEPTH_tb),
                .ADDR_WIDTH(ADDR_WIDTH_tb)
) DUT (
                .W_CLK(W_CLK_tb),
                .W_RST(W_RST_tb),
                .W_INC(W_INC_tb),
                .R_CLK(R_CLK_tb),
                .R_RST(R_RST_tb),
                .R_INC(R_INC_tb),
                .WR_DATA(WR_DATA_tb),
                .FULL(FULL_tb),
                .EMPTY(EMPTY_tb),
                .RD_DATA(RD_DATA_tb)
);

// Generating the write Clock (10 ns => 100 MHz)
always #(W_CLK_PERIOD / 2) W_CLK_tb = ~ W_CLK_tb;

// Generating the read clock (25 ns => 40 MHz)
always #(R_CLK_PERIOD / 2.0) R_CLK_tb = ~ R_CLK_tb;

// Initial block for setup and write operations
initial 
    begin
        // System Functions
        $dumpfile("ASYC_FIFO.vcd");       
        $dumpvars;
        
        // Starting Simulation
        $display("----------------------------");
        $display("Starting Simulation for ASYC_FIFO");
        
        // Initialize Signals
        w_initialize();

        // Apply active-low reset for the write side
        w_reset();

        // Write data
        write_data(10);
    end 
    
// Initial block for read operations and final simulation control
initial begin
    // Initialize Read side signals
    rd_initialize();

    // Apply active-low reset for the read side
    rd_reset();
    
    // Loop to read data
    read_data(10);

    // End of simulation after a short delay
    #(6 * R_CLK_PERIOD);
    $display("----------------------------");
    $display("Simulation Finished");
    $stop;
end

//Tasks
task w_initialize;
    begin
        // Write initialize
        W_CLK_tb = 0;
        W_INC_tb = 0;
        WR_DATA_tb = 0;
        wr_index = 0;
    end
endtask

task w_reset;
    begin
        // Write reset
        W_RST_tb = 1'b0;        
        #(W_CLK_PERIOD);
        W_RST_tb = 1'b1;
    end
endtask

task write_data;
    input [3:0] repeat_count_wr;
    begin
        #(2*W_CLK_PERIOD);        
        repeat (repeat_count_wr) begin
            @(negedge W_CLK_tb);
            // Increment data on each write for easier debugging. Note: WR_DATA_tb will be 1 on the first write
            WR_DATA_tb = WR_DATA_tb + 1;    
            W_INC_tb = 1'b1;
            @(posedge W_CLK_tb);

            if (!FULL_tb)
                begin
                    expected_data[wr_index] = WR_DATA_tb;
                    $display("Wrote 0x%0h to FIFO mem in address %0d", WR_DATA_tb, wr_index);
                    if (wr_index < 7)
                        wr_index = wr_index + 1;
                    else
                        wr_index = 0;
                end
        end
        
        @(negedge W_CLK_tb);
        W_INC_tb = 1'b0;                // Deassert write enable
    end
endtask

task rd_initialize;
    begin
        // Read Initialize
        R_CLK_tb = 0;
        R_INC_tb = 0;
        rd_index = 0;
    end
endtask

task rd_reset;
    begin
        // Read Reset
        R_RST_tb = 1'b0;
        #(R_CLK_PERIOD);
        R_RST_tb = 1'b1;
    end
endtask

task read_data;
    input [3:0] repeat_count_rd;
    begin
        // Wait for 2 clock cycles and then start the burst read
        // For testing
        #(2 * R_CLK_PERIOD);
        R_INC_tb = 1'b1;

        // Data is available on the NEXT clock edge after R_INC is asserted
        // We loop and check the data at each subsequent clock edge
        repeat (repeat_count_rd)
            begin
                @(posedge R_CLK_tb);            // Wait for the next clock edge for data to be valid
                
                // Now, check the data from the previously initiated read
                $display("Checking index %0d. Read: 0x%0h, Expected: 0x%0h", rd_index, RD_DATA_tb, expected_data[rd_index]);
                if (RD_DATA_tb == expected_data[rd_index])
                    $display("Test Case Passed");
                else
                    $display("Test Case Failed");
                
                if(rd_index < 7)
                    rd_index = rd_index + 1;
                else
                    rd_index = 0;
            end 
        
        // After the burst read is complete, deassert the read enable
        @(negedge R_CLK_tb);
        R_INC_tb = 1'b0;
    end
endtask

endmodule

FIFO/ASYC_FIFO.vcd
$date
	Mon Sep 08 22:58:10 2025
$end
$version
	ModelSim Version 10.5b
$end
$timescale
	1ps
$end

$scope module ASYC_FIFO_tb $end
$var parameter 32 ! DATA_WIDTH_tb $end
$var parameter 32 " DEPTH_tb $end
$var parameter 32 # ADDR_WIDTH_tb $end
$var parameter 32 $ W_CLK_PERIOD $end
$var parameter 0 % R_CLK_PERIOD $end
$var reg 1 & W_CLK_tb $end
$var reg 1 ' W_RST_tb $end
$var reg 1 ( W_INC_tb $end
$var reg 1 ) R_CLK_tb $end
$var reg 1 * R_RST_tb $end
$var reg 1 + R_INC_tb $end
$var reg 8 , WR_DATA_tb [7:0] $end
$var wire 1 - FULL_tb $end
$var wire 1 . EMPTY_tb $end
$var wire 1 / RD_DATA_tb [7] $end
$var wire 1 0 RD_DATA_tb [6] $end
$var wire 1 1 RD_DATA_tb [5] $end
$var wire 1 2 RD_DATA_tb [4] $end
$var wire 1 3 RD_DATA_tb [3] $end
$var wire 1 4 RD_DATA_tb [2] $end
$var wire 1 5 RD_DATA_tb [1] $end
$var wire 1 6 RD_DATA_tb [0] $end
$var integer 32 7 wr_index $end
$var integer 32 8 rd_index $end

$scope task w_initialize $end
$upscope $end

$scope task w_reset $end
$upscope $end

$scope task write_data $end
$var reg 4 9 repeat_count_wr [3:0] $end
$upscope $end

$scope task rd_initialize $end
$upscope $end

$scope task rd_reset $end
$upscope $end

$scope task read_data $end
$var reg 4 : repeat_count_rd [3:0] $end
$upscope $end

$scope module DUT $end
$var parameter 32 ; DATA_WIDTH $end
$var parameter 32 < DEPTH $end
$var parameter 32 = ADDR_WIDTH $end
$var wire 1 > W_CLK $end
$var wire 1 ? W_RST $end
$var wire 1 @ W_INC $end
$var wire 1 A R_CLK $end
$var wire 1 B R_RST $end
$var wire 1 C R_INC $end
$var wire 1 D WR_DATA [7] $end
$var wire 1 E WR_DATA [6] $end
$var wire 1 F WR_DATA [5] $end
$var wire 1 G WR_DATA [4] $end
$var wire 1 H WR_DATA [3] $end
$var wire 1 I WR_DATA [2] $end
$var wire 1 J WR_DATA [1] $end
$var wire 1 K WR_DATA [0] $end
$var wire 1 - FULL $end
$var wire 1 . EMPTY $end
$var wire 1 / RD_DATA [7] $end
$var wire 1 0 RD_DATA [6] $end
$var wire 1 1 RD_DATA [5] $end
$var wire 1 2 RD_DATA [4] $end
$var wire 1 3 RD_DATA [3] $end
$var wire 1 4 RD_DATA [2] $end
$var wire 1 5 RD_DATA [1] $end
$var wire 1 6 RD_DATA [0] $end
$var wire 1 L W_ADDR [2] $end
$var wire 1 M W_ADDR [1] $end
$var wire 1 N W_ADDR [0] $end
$var wire 1 O R_ADDR [2] $end
$var wire 1 P R_ADDR [1] $end
$var wire 1 Q R_ADDR [0] $end
$var wire 1 R rptr_in [3] $end
$var wire 1 S rptr_in [2] $end
$var wire 1 T rptr_in [1] $end
$var wire 1 U rptr_in [0] $end
$var wire 1 V wptr_in [3] $end
$var wire 1 W wptr_in [2] $end
$var wire 1 X wptr_in [1] $end
$var wire 1 Y wptr_in [0] $end
$var wire 1 Z rptr_out [3] $end
$var wire 1 [ rptr_out [2] $end
$var wire 1 \ rptr_out [1] $end
$var wire 1 ] rptr_out [0] $end
$var wire 1 ^ wptr_out [3] $end
$var wire 1 _ wptr_out [2] $end
$var wire 1 ` wptr_out [1] $end
$var wire 1 a wptr_out [0] $end

$scope module mem $end
$var parameter 32 b DATA_WIDTH $end
$var parameter 32 c DEPTH $end
$var parameter 32 d ADDR_WIDTH $end
$var wire 1 > w_clk $end
$var wire 1 ? w_rst $end
$var wire 1 - FULL $end
$var wire 1 @ w_inc $end
$var wire 1 L w_addr [2] $end
$var wire 1 M w_addr [1] $end
$var wire 1 N w_addr [0] $end
$var wire 1 O r_addr [2] $end
$var wire 1 P r_addr [1] $end
$var wire 1 Q r_addr [0] $end
$var wire 1 D w_data [7] $end
$var wire 1 E w_data [6] $end
$var wire 1 F w_data [5] $end
$var wire 1 G w_data [4] $end
$var wire 1 H w_data [3] $end
$var wire 1 I w_data [2] $end
$var wire 1 J w_data [1] $end
$var wire 1 K w_data [0] $end
$var wire 1 / r_data [7] $end
$var wire 1 0 r_data [6] $end
$var wire 1 1 r_data [5] $end
$var wire 1 2 r_data [4] $end
$var wire 1 3 r_data [3] $end
$var wire 1 4 r_data [2] $end
$var wire 1 5 r_data [1] $end
$var wire 1 6 r_data [0] $end
$var wire 1 e w_clken $end
$var integer 32 f i $end
$upscope $end

$scope module df1_w $end
$var parameter 32 g ADDR_WIDTH $end
$var wire 1 > clk $end
$var wire 1 ? rst $end
$var wire 1 R data_in [3] $end
$var wire 1 S data_in [2] $end
$var wire 1 T data_in [1] $end
$var wire 1 U data_in [0] $end
$var reg 4 h data_out [3:0] $end
$var reg 4 i ff1 [3:0] $end
$upscope $end

$scope module df2_r $end
$var parameter 32 j ADDR_WIDTH $end
$var wire 1 A clk $end
$var wire 1 B rst $end
$var wire 1 V data_in [3] $end
$var wire 1 W data_in [2] $end
$var wire 1 X data_in [1] $end
$var wire 1 Y data_in [0] $end
$var reg 4 k data_out [3:0] $end
$var reg 4 l ff1 [3:0] $end
$upscope $end

$scope module WR $end
$var parameter 32 m ADDR_WIDTH $end
$var wire 1 @ w_inc $end
$var wire 1 > w_clk $end
$var wire 1 ? w_rst $end
$var wire 1 Z gray_rptr [3] $end
$var wire 1 [ gray_rptr [2] $end
$var wire 1 \ gray_rptr [1] $end
$var wire 1 ] gray_rptr [0] $end
$var wire 1 V gray_wptr [3] $end
$var wire 1 W gray_wptr [2] $end
$var wire 1 X gray_wptr [1] $end
$var wire 1 Y gray_wptr [0] $end
$var wire 1 L w_addr [2] $end
$var wire 1 M w_addr [1] $end
$var wire 1 N w_addr [0] $end
$var wire 1 - FULL $end
$var reg 4 n bin_wptr [3:0] $end
$upscope $end

$scope module RD $end
$var parameter 32 o ADDR_WIDTH $end
$var wire 1 A r_clk $end
$var wire 1 B r_rst $end
$var wire 1 C r_inc $end
$var wire 1 ^ gray_wptr [3] $end
$var wire 1 _ gray_wptr [2] $end
$var wire 1 ` gray_wptr [1] $end
$var wire 1 a gray_wptr [0] $end
$var wire 1 R gray_rptr [3] $end
$var wire 1 S gray_rptr [2] $end
$var wire 1 T gray_rptr [1] $end
$var wire 1 U gray_rptr [0] $end
$var wire 1 O r_addr [2] $end
$var wire 1 P r_addr [1] $end
$var wire 1 Q r_addr [0] $end
$var wire 1 . EMPTY $end
$var reg 4 p bin_rptr [3:0] $end
$upscope $end
$upscope $end
$upscope $end
$enddefinitions $end
#0
$dumpvars
0&
0'
0(
0)
0*
0+
b0 ,
b0 h
b0 i
b0 k
b0 l
b0 n
b0 p
bx 9
bx :
b1000 !
b1000 "
b11 #
b1010 $
b1000 ;
b1000 <
b11 =
b1000 b
b1000 c
b11 d
b11 g
b11 j
b11 m
b11 o
r25 %
b0 7
b0 8
b1000 f
0-
1.
06
05
04
03
02
01
00
0/
0N
0M
0L
0Q
0P
0O
0U
0T
0S
0R
0Y
0X
0W
0V
0]
0\
0[
0Z
0a
0`
0_
0^
0e
0K
0J
0I
0H
0G
0F
0E
0D
0C
0B
0A
0@
0?
0>
$end
#5000
1&
1>
b0 f
b1 f
b10 f
b11 f
b100 f
b101 f
b110 f
b111 f
b1000 f
#10000
1'
b1010 9
0&
1?
0>
#12500
1)
1A
#15000
1&
1>
#20000
0&
0>
#25000
1*
b1010 :
0)
1&
1B
0A
1>
#30000
0&
0>
b1 ,
1(
1K
1@
1e
#35000
1&
1>
b1 7
b1 n
1Y
1N
16
#37500
1)
1A
b1 l
#40000
0&
0>
b10 ,
0K
1J
#45000
1&
1>
b10 7
b10 n
1X
0N
1M
#50000
0)
0&
0A
0>
b11 ,
1K
#55000
1&
1>
b11 7
b11 n
0Y
1N
#60000
0&
0>
b100 ,
0K
0J
1I
#62500
1)
1A
b10 l
b1 k
1a
0.
#65000
1&
1>
b100 7
b100 n
1W
0N
0M
1L
#70000
0&
0>
b101 ,
1K
#75000
1+
0)
1&
1C
0A
1>
b101 7
b101 n
1Y
1N
#80000
0&
0>
b110 ,
0K
1J
#85000
1&
1>
b110 7
b110 n
0X
0N
1M
#87500
1)
1A
b1 8
b101 l
b10 k
b1 p
1U
1Q
0a
1`
06
15
#90000
0&
0>
b111 ,
1K
#95000
1&
1>
b111 7
b1 i
b111 n
0Y
1N
#100000
0)
0&
0A
0>
b1000 ,
0K
0J
0I
1H
#105000
1&
1>
b0 7
b1 h
b1000 n
1V
0N
0M
0L
1]
#110000
0&
0>
b1001 ,
1K
#112500
1)
1A
b10 8
b1100 l
b101 k
b10 p
1T
0Q
1P
1a
0`
1_
16
#115000
1&
1>
b1 7
b11 i
b1001 n
1Y
1N
1-
0e
#120000
0&
0>
b1010 ,
0K
1J
#125000
0)
1&
0A
1>
b11 h
1\
0-
1e
#130000
0&
0>
0(
0@
0e
#135000
1&
1>
#137500
1)
1A
b11 8
b1101 l
b1100 k
b11 p
0U
1Q
0a
1^
06
05
14
#140000
0&
0>
#145000
1&
1>
b10 i
#150000
0)
0&
0A
0>
#155000
1&
1>
b10 h
0]
#160000
0&
0>
#162500
1)
1A
b100 8
b1101 k
b100 p
1S
0Q
0P
1O
1a
16
#165000
1&
1>
b110 i
#170000
0&
0>
#175000
0)
1&
0A
1>
b110 h
1[
#180000
0&
0>
#185000
1&
1>
#187500
1)
1A
b101 8
b101 p
1U
1Q
06
15
#190000
0&
0>
#195000
1&
1>
b111 i
#200000
0)
0&
0A
0>
#205000
1&
1>
b111 h
1]
#210000
0&
0>
#212500
1)
1A
b110 8
b110 p
0T
0Q
1P
16
#215000
1&
1>
b101 i
#220000
0&
0>
#225000
0)
1&
0A
1>
b101 h
0\
#230000
0&
0>
#235000
1&
1>
#237500
1)
1A
b111 8
b111 p
0U
1Q
06
05
04
13
#240000
0&
0>
#245000
1&
1>
b100 i
#250000
0)
0&
0A
0>
#255000
1&
1>
b100 h
0]
#260000
0&
0>
#262500
1)
1A
b0 8
b1000 p
1R
0Q
0P
0O
16
#265000
1&
1>
b1100 i
#270000
0&
0>
#275000
0)
1&
0A
1>
b1100 h
1Z
#280000
0&
0>
#285000
1&
1>
#287500
1)
1A
b1 8
b1001 p
1U
1Q
1.
06
15
03
#290000
0&
0>
#295000
1&
1>
b1101 i
#300000
0)
0&
0A
0>
#305000
1&
1>
b1101 h
1]
#310000
0&
0>
#312500
1)
1A
b10 8
#315000
1&
1>
#320000
0&
0>
#325000
0)
1&
0A
1>
0+
0C
